terminal_password.cp37-win_amd64.pyd
terminal_password-0.1.1.data/data/terminal_password.gif
terminal_password-0.1.1.dist-info/METADATA
terminal_password-0.1.1.dist-info/WHEEL
terminal_password-0.1.1.dist-info/top_level.txt
terminal_password-0.1.1.dist-info/RECORD
