Metadata-Version: 2.1
Name: terminal-password
Version: 0.1.1
Summary: a tool for input cipher password
Home-page: UNKNOWN
License: UNKNOWN
Keywords: password,terminal
Platform: any
Classifier: Programming Language :: Python :: 3
Classifier: Programming Language :: Python :: 3.7
Classifier: Programming Language :: Python :: 3.8
Classifier: Programming Language :: Python :: 3.9
Requires-Python: >=3.4
